prpl/__init__.py
prpl/prpl.py
prpl/prpl_for_loop_progress.py
prpl/prpl_progress.py
prpl/prpl_progress_simple.py
progress_parallel-3.2.1.dist-info/LICENSE
progress_parallel-3.2.1.dist-info/METADATA
progress_parallel-3.2.1.dist-info/WHEEL
progress_parallel-3.2.1.dist-info/top_level.txt
progress_parallel-3.2.1.dist-info/RECORD
