Metadata-Version: 2.1
Name: progress-parallel
Version: 3.2.1
Summary: multi threading progress bar
Home-page: https://github.com/Domzou-kun/prpl
Download-URL: https://github.com/Domzou-kun/prpl
Author: Domzou
License: MIT
Keywords: Python python progress multi thread threading
Classifier: Operating System :: Microsoft :: Windows :: Windows 10
Classifier: Programming Language :: Python :: 3.8
Classifier: Programming Language :: Python :: 3.9
Classifier: Programming Language :: Python :: 3.10
Classifier: Topic :: Software Development :: Libraries :: Python Modules
Classifier: Topic :: System :: Archiving :: Packaging
License-File: LICENSE
